caerp_base/__init__.py
caerp_base/consts.py
caerp_base/exception.py
caerp_base/mail.py
caerp_base/models/__init__.py
caerp_base/models/base.py
caerp_base/models/initialize.py
caerp_base/models/mixins.py
caerp_base/models/types.py
caerp_base/models/utils.py
caerp_base-2025.1.0.dist-info/LICENSE.txt
caerp_base-2025.1.0.dist-info/METADATA
caerp_base-2025.1.0.dist-info/WHEEL
caerp_base-2025.1.0.dist-info/entry_points.txt
caerp_base-2025.1.0.dist-info/top_level.txt
caerp_base-2025.1.0.dist-info/RECORD
